README.md
setup.cfg
setup.py
pyz/__init__.py
pyz.egg-info/PKG-INFO
pyz.egg-info/SOURCES.txt
pyz.egg-info/dependency_links.txt
pyz.egg-info/top_level.txt