Metadata-Version: 1.1
Name: pyz
Version: 0.3.0
Summary: Packages all source code and dependencies into a single Python zip application.
Home-page: https://github.com/BTOdell/pyz
Author: Bradley Odell
Author-email: btodell@hotmail.com
License: GPLv3
Download-URL: https://github.com/BTOdell/pyz/archive/0.3.0.tar.gz
Keywords: pyz zip app zipapp bundle dependencies library
Platform: UNKNOWN
Classifier: Development Status :: 3 - Alpha
Classifier: Environment :: Console
Classifier: Intended Audience :: Developers
Classifier: License :: OSI Approved :: GNU General Public License v3 (GPLv3)
Classifier: Natural Language :: English
Classifier: Operating System :: OS Independent
Classifier: Programming Language :: Python :: 2.6
Classifier: Programming Language :: Python :: 2.7
Classifier: Programming Language :: Python :: 3
Classifier: Topic :: Software Development :: Build Tools
